crawfish/__init__.py
crawfish/apps.py
crawfish/context_processors.py
crawfish/emails.py
crawfish/exceptions.py
crawfish/middleware.py
crawfish/mixins.py
crawfish/pagination.py
crawfish/utils.py
crawfish/models/__init__.py
crawfish/models/fields.py
crawfish/models/models.py
django_crawfish-0.0.18.dist-info/LICENSE
django_crawfish-0.0.18.dist-info/METADATA
django_crawfish-0.0.18.dist-info/WHEEL
django_crawfish-0.0.18.dist-info/top_level.txt
django_crawfish-0.0.18.dist-info/RECORD
