Metadata-Version: 2.1
Name: django-crawfish
Version: 0.0.18
Summary: pending...
Home-page: https://gitlab.com/crawfordleeds/crawfish
Author: Crawford Leeds
Author-email: crawford@crawfordleeds.com
License: MIT
Platform: UNKNOWN
Classifier: Development Status :: 2 - Pre-Alpha
Classifier: Intended Audience :: Developers
Classifier: License :: OSI Approved :: MIT License
Classifier: Natural Language :: English
Classifier: Programming Language :: Python :: 3
Classifier: Programming Language :: Python :: 3.6
Classifier: Programming Language :: Python :: 3.7
Classifier: Programming Language :: Python :: 3.8
Classifier: Framework :: Django :: 2.2
Classifier: Framework :: Django :: 3.0
Classifier: Framework :: Django :: 3.1
Requires-Python: >=3.6
License-File: LICENSE
Requires-Dist: Django (>=2.2)
Provides-Extra: dev
Requires-Dist: black (==20.8b1) ; extra == 'dev'
Requires-Dist: bumpversion (==0.6.0) ; extra == 'dev'
Requires-Dist: tox (==3.20.1) ; extra == 'dev'
Requires-Dist: coverage (==5.3) ; extra == 'dev'
Requires-Dist: twine (==3.2.0) ; extra == 'dev'
Requires-Dist: djangorestframework (==3.12.2) ; extra == 'dev'
Requires-Dist: sphinx-rtd-theme (==1.0.0) ; extra == 'dev'
Requires-Dist: sphinx (==4.2.0) ; extra == 'dev'
